dpx_control/__init__.py
dpx_control/api.py
dpx_control/api_test.py
dpx_control/bin_edges_random.py
dpx_control/config.py
dpx_control/control.py
dpx_control/dpx_functions.py
dpx_control/dpx_settings.py
dpx_control/dpx_support.py
dpx_control/dpx_test_pulse.py
dpx_control/support.py
dpx_control/system.py
dpx_control-0.3.3.dist-info/LICENSE
dpx_control-0.3.3.dist-info/METADATA
dpx_control-0.3.3.dist-info/WHEEL
dpx_control-0.3.3.dist-info/entry_points.txt
dpx_control-0.3.3.dist-info/top_level.txt
dpx_control-0.3.3.dist-info/RECORD
