Metadata-Version: 2.1
Name: dpx-control
Version: 0.3.3
Summary: DPX control software
Home-page: https://github.com/dosepix/dpx_control
Author: Sebastian Schmidt
Author-email: schm.seb@gmail.com
License: GNU GPLv3
Project-URL: Bug Tracker, https://github.com/dosepix/dpx_control/issues
Platform: UNKNOWN
Classifier: Programming Language :: Python :: 3
Classifier: License :: OSI Approved :: GNU General Public License v3 (GPLv3)
Classifier: Operating System :: OS Independent
Requires-Dist: configparser
Requires-Dist: matplotlib
Requires-Dist: numpy
Requires-Dist: pyserial
Requires-Dist: scipy
Requires-Dist: tqdm
